setup.py
ChineseWordPiece/__init__.py
ChineseWordPiece/quiry.py
ChineseWordPiece.egg-info/PKG-INFO
ChineseWordPiece.egg-info/SOURCES.txt
ChineseWordPiece.egg-info/dependency_links.txt
ChineseWordPiece.egg-info/top_level.txt
ChineseWordPiece/data/__init__.py