Metadata-Version: 1.0
Name: ChineseWordPiece
Version: 1.0.2
Summary: WordPiece for Chinese Words
Home-page: https://github.com/soap117/ChineseWordPiece
Author: Junyu Luo
Author-email: asbljy@outlook.com
License: MIT Licence
Keywords: pip,ChineseWordPiece,WordPiece
Platform: any
